Workbook
Name SegmentaçãodeDados_CLIENTE_TOMADOR: #N/A
Name SegmentaçãodeDados_SERVICO: #N/A

Sheet Base
A1: MINUTA | B1: BASE | C1: DATA COLETA | D1: DATA | E1: FAT | F1: CT-E | G1: CLIENTE TOMADOR | H1: VENDEDOR | I1: VALOR NF | J1: SERVICO | K1: TIPO CTE | L1: DESTINO | M1: FRETE | N1: VOLUMES | O1: PESO | P1: RESP. COLETA | Q1: CUSTO COLETA | R1: RESP. ENTREGA | S1: CUSTO ENTREGA | T1: RESP. TRANSF | U1: CUSTO TRANSF | V1: ICMS/ISS | W1: DIFAL | X1: C.DESPACHO | Y1: SEGURO | Z1: OUTROS | AA1: C.TOTAL | AB1: RECEITA | AC1: IMPOSTO | AD1: RESULTADO | AE1: COMIS | AF1: LUCRO LIQ | AG1: MARGEM | AH1: Coluna1
A2: 2827 | B2: MATRIZ | C2: 46265 | D2: 46265 | E2: 477 | F2: 2738-1 | G2: AC COMERCIAL IM | H2: TIAGO SANTANA | I2: 405994.28 | J2: PERSONALIZADO_L | K2: CTE NORMAL | L2: ITAPEVA - MG | M2: 6370.44 | N2: 43 | O2: 823.5 | P2: MATRIZ | Q2: 0 | R2: RODRIGO DA SILVA POLEZA | S2: 3700 | T2: INDEFINIDO | U2: 0 | V2: 764.45 | W2: 0 | X2: 0 | Y2: 162.4 | Z2: 0 | AA2: 4626.85 | AB2: 1743.59 | AC2: 1019.27 | AD2: 724.32 | AE2: 56.06 | AF2: 668.26 | AG2: 0.1049

Sheet Análise
E1: FATURAMENTO
E2: Faturamento | H2: Peso | J2: Venda KG | M2: Veículo | P2: Peso Veículo | S2: Taxa Ocupação Veículo
E3: ='Resumo Detalhado'!B2 -> 6370.44 | H3: ='Resumo Detalhado'!C2 -> 823.5 | J3: =E3/H3 -> 7.7358106 | M3: Van | P3: 1200 | S3: =MIN(H3/P3,1) -> 0.68625
E5: CUSTO VARIÁVEL SINTÉTICO
E6: C.Variável Total | J6: Custo KG Total CV | M6: % Fat x C.V Total | P6: Custo Total | S6: Custo KG Total
E7: =E11+K11+Q11 -> 3100 | J7: =E7/H3 -> 3.7644202 | M7: =E7/E3 -> 0.48662259 | P7: =E11+K11+Q11+E15+K15+Q15+E19+H19+K19 -> 6155.7556 | S7: =P7/H3 -> 7.4751131
E9: CUSTO VARIÁVEL ANÁLITICO
E10: C.Transf. | H10: Custo KG Transf. | K10: C.Entrega | N10: Custo KG Entrega | Q10: C.Coleta | T10: Custo KG Coleta
D11: =IF(E11=0,K11,E11) -> 3100 | E11: =ROUNDUP('Resumo Detalhado'!F2,0) -> 0 | H11: =E11/H3 -> 0 | K11: 3100 | N11: =K11/H3 -> 3.7644202 | Q11: ='Resumo Detalhado'!D2 -> 0 | T11: =Q11/H3 -> 0 | W11: TIPO DE VEÍCULO | Y11: CAP.PESO
W12: Carreta | Y12: 22000
E13: IMPOSTOS | W13: Truck | Y13: 11000
E14: C.Icms | K14: I.Federais + C.Fixo | W14: Toco | Y14: 6000
E15: ='Resumo Detalhado'!H2 -> 764.45 | K15: ='Resumo Detalhado'!K2+'Resumo Detalhado'!L2 -> 1019.2704 | W15: 3/4 | Y15: 3500
W16: Van | Y16: 1200
E17: OUTROS CUSTOS | O17: TARGET
E18: C.Seguro | H18: C.M.O(Outros) | K18: C.Comissão | N18: TRECHO | S18: VALOR | W18: STATUS DA CONTRATAÇÃO
E19: ='Resumo Detalhado'!I2 -> 162.4 | H19: 600 | K19: ='Resumo Detalhado'!L2 -> 509.6352 | N19: Itajai-Sc X Itapeva-Mgvan | S19: 3100 | W19: =IF(D11=S19,"NO TARGET",IF(D11<S19,"ABAIXO DO TARGET",IF(D11>S19,"FORA DO TARGET"))) -> NO TARGET
E21: RESULTADO
E22: Resultado Operacional | N22: Margem Bruta
E23: ='Resumo Detalhado'!N2 -> 668.2596 | N23: =E23/E3 -> 0.10490007

Sheet Resumo Detalhado
A1: SERVICO | B1: (Tudo)
B2: =SUM(B6:B5000) -> 6370.44 | C2: =SUM(C6:C5000) -> 823.5 | D2: =SUM(D6:D5000) -> 0 | E2: =SUM(E6:E5000) -> 3700 | F2: =SUM(F6:F5000) -> 0 | H2: =SUM(H6:H5000) -> 764.45 | I2: =SUM(I6:I5000) -> 162.4 | J2: =SUM(J6:J5000) -> 0 | K2: =SUM(K6:K5000) -> 509.6352 | L2: =SUM(L6:L5000) -> 509.6352 | M2: =SUM(M6:M5000) -> 56.06 | N2: =SUM(N6:N5000) -> 668.2596 | O2: =SUM(O6:O5000) -> #DIV/0! | P2: =SUM(P6:P5000) -> 0
B3: Valores
A4: CLIENTE | B4: FATURAMENTO | C4: PESO FAT. | D4: C.COLETA | E4: C.ENTREGA | F4: C.TRANSF | G4: META C.VARIÁVEL | H4: C.ICMS | I4: C.SEGURO | J4: C.OUTROS | K4: I.FEDERAIS. | L4: C.FIXO. | M4: C.COMIS | N4: Resultado Oper. | O4: MARGEM BRUTA.
A5: AC COMERCIAL IM
A6: 2827 | B6: 6370.44 | C6: 823.5 | D6: 0 | E6: 3700 | F6: 0 | G6: 0.58080761 | H6: 764.45 | I6: 162.4 | J6: 0 | K6: 509.6352 | L6: 509.6352 | M6: 56.06 | N6: 668.2596 | O6: 0.10490007
A7: (vazio)
A8: (vazio) | G8: #DIV/0! | K8: 0 | L8: 0 | N8: 0 | O8: #DIV/0!

Sheet Resumo Detalhado Grafico
A1: SERVICO | B1: (Tudo)
B2: =SUM(B6:B5000) -> 0 | C2: =SUM(C6:C5000) -> 0
B3: Valores
A4: CLIENTE | B4: Faturamento. | C4: Resultado Oper.
A5: AC COMERCIAL IM | B5: 6370.44 | C5: 668.2596
A6: (vazio) | C6: 0

Sheet Target
A1: TRECHO | B1: TIPO VEÍCULO | C1: CONCATENADO | D1: VALOR
A2: Ascurra-Sc X Itajai-Sc | B2: 3/4 | C2: Ascurra-Sc X Itajai-Sc3/4 | D2: 800
A3: Barueri-Sp X São Paulo-Sp | B3: truck | C3: Barueri-Sp X São Paulo-Sptruck | D3: 900
A4: Belo Horizonte-Mg X Garuva-Sc | B4: van | C4: Belo Horizonte-Mg X Garuva-Scvan | D4: 4300
A5: Belo Horizonte-Mg X Itajai-Sc | B5: fiorino | C5: Belo Horizonte-Mg X Itajai-Scfiorino | D5: 3500
A6: Biguaçu-Sc X São Paulo-Sp | B6: van | C6: Biguaçu-Sc X São Paulo-Spvan | D6: 2500
A7: Blumenau-Sc X Guarulhos-Sp | B7: carreta | C7: Blumenau-Sc X Guarulhos-Spcarreta | D7: 5500
A8: Blumenau-Sc X Guarulhos-Sp | B8: truck | C8: Blumenau-Sc X Guarulhos-Sptruck | D8: 4100
A9: Blumenau-Sc X Suzano-Sp | B9: truck | C9: Blumenau-Sc X Suzano-Sptruck | D9: 4300
A10: Camboriu-Sc X Cabo de Santo Agostinho-Pe | B10: 3/4 | C10: Camboriu-Sc X Cabo de Santo Agostinho-Pe3/4 | D10: 14800
A11: Camboriu-Sc X Cabo de Santo Agostinho-Pe | B11: truck | C11: Camboriu-Sc X Cabo de Santo Agostinho-Petruck | D11: 18000
A12: Camboriu-Sc X Cabo de Santo Agostinho-Pe | B12: carreta | C12: Camboriu-Sc X Cabo de Santo Agostinho-Pecarreta | D12: 25000
A13: Camboriu-Sc X Cajamar-Sp | B13: 3/4 | C13: Camboriu-Sc X Cajamar-Sp3/4 | D13: 3200
... A177: Pomerode-Sc X Guarulhos-Sp | B177: toco | C177: Pomerode-Sc X Guarulhos-Sptoco | D177: 4000
A178: Navegantes-Sc X Cajamar-Sp | B178: 46085 | C178: Navegantes-Sc X Cajamar-Sp3/4 | D178: 3200
A179: Pomerode-Sc X Guarulhos-Sp | B179: truck | C179: Pomerode-Sc X Guarulhos-Sptruck | D179: 4100
A180: Sao Paulo-Sp X Brasilia-Df | B180: 46085 | C180: Sao Paulo-Sp X Brasilia-Df3/4 | D180: 5800
A181: Navegantes-Sc X Guarulhos-Sp | B181: truck | C181: Navegantes-Sc X Guarulhos-Sptruck | D181: 4100
A182: Itajai-Sc X Sao Paulo-Sp | B182: truck | C182: Itajai-Sc X Sao Paulo-Sptruck | D182: 4000
A183: Sao Paulo-Sp X Contagem-Mg | B183: truck | C183: Sao Paulo-Sp X Contagem-Mgtruck | D183: 3800
A184: Itajai-Sc X Rio de Janeiro-Rj | B184: fiorino | C184: Itajai-Sc X Rio de Janeiro-Rjfiorino | D184: 3500
A185: São Paulo-Sp X São Paulo-Sp | B185: truck | C185: São Paulo-Sp X São Paulo-Sptruck | D185: 1200
A186: Vinhedo-Sp X Guarulhos-Sp | B186: carreta | C186: Vinhedo-Sp X Guarulhos-Spcarreta | D186: 2300
A187: Itajai-Sc X Caxias do Sul-Rs | B187: 46085 | C187: Itajai-Sc X Caxias do Sul-Rs3/4 | D187: 3200
A188: São Paulo-Sp X Cascavel-Pr | B188: truck | C188: São Paulo-Sp X Cascavel-Prtruck | D188: 5000
C189: Itajai-Sc X Colombo-Prvan | D189: 1500
C190: São Paulo-Sp X Itapeva-SpVan | D190: 1900
C191: Araraquara-Sp X Santos-Sp3/4 | D191: 1800
C192: Campinas-Sp X Suzano-Spcarreta | D192: 2500
C193: Garuva-Sc X Itajai-Sc3/4 | D193: 800
C194: Guarulhos-Sp X São Paulo-Sptruck | D194: 1200
C195: Itajai-Sc X Arapongas-Pr3/4 | D195: 3200
C196: Itajai-Sc X Balneario Camboriu-Scvan | D196: 580
C197: Itajai-Sc X Blumenau-Scfiorino | D197: 400
C198: Itajai-Sc X Blumenau-Sctoco | D198: 900
C199: Itajai-Sc X Blumenau-Sctruck | D199: 1200
C200: Itajai-Sc X Blumenau-Sccarreta | D200: 1500
... C368: Itajai-Sc X Itapeva-Mgvan | D368: 3100
