Workbook
Name SegmentaçãodeDados_CLIENTE_TOMADOR: #N/A
Name SegmentaçãodeDados_SERVICO: #N/A

Sheet Base
A1: MINUTA | B1: BASE | C1: DATA COLETA | D1: DATA | E1: FAT | F1: CT-E | G1: CLIENTE TOMADOR | H1: VENDEDOR | I1: VALOR NF | J1: SERVICO | K1: TIPO CTE | L1: DESTINO | M1: FRETE | N1: VOLUMES | O1: PESO | P1: RESP. COLETA | Q1: CUSTO COLETA | R1: RESP. ENTREGA | S1: CUSTO ENTREGA | T1: RESP. TRANSF | U1: CUSTO TRANSF | V1: ICMS/ISS | W1: DIFAL | X1: C.DESPACHO | Y1: SEGURO | Z1: OUTROS | AA1: C.TOTAL | AB1: RECEITA | AC1: IMPOSTO | AD1: RESULTADO | AE1: COMIS | AF1: LUCRO LIQ | AG1: MARGEM | AH1: Coluna1
A2: 302534 | B2: FILIAL SP | C2: 46289 | D2: 46293 | F2: 37912-1 | G2: ANSELL BRAZIL L | H2: MARLON MARQUES | I2: 12968.59 | J2: EXPRESSO_250 | K2: CTE NORMAL | L2: CRICIUMA - SC | M2: 299.17 | N2: 12 | O2: 86.36 | P2: FILIAL SP | Q2: 89.58 | R2: MF EXPRESS TRANSPORTE ROD | S2: 104.71 | T2: G.S CITRUS COMERCIO ATACA | U2: 40.82 | V2: 35.9 | W2: 0 | X2: 0 | Y2: 6.48 | Z2: 0 | AA2: 277.49 | AB2: 21.68 | AC2: 77.78 | AD2: -56.1 | AE2: 0 | AF2: -56.1 | AG2: -0.1875
A3: 302617 | B3: FILIAL SP | C3: 46289 | D3: 46293 | F3: 37903-1 | G3: ANSELL BRAZIL L | H3: MARLON MARQUES | I3: 1905.4 | J3: EXPRESSO_250 | K3: CTE NORMAL | L3: CRICIUMA - SC | M3: 145.78 | N3: 1 | O3: 6.62 | P3: FILIAL SP | Q3: 6.87 | R3: MF EXPRESS TRANSPORTE ROD | S3: 51.02 | T3: G.S CITRUS COMERCIO ATACA | U3: 3.13 | V3: 17.49 | W3: 0 | X3: 0 | Y3: 0.95 | Z3: 0 | AA3: 79.46 | AB3: 66.32 | AC3: 37.9 | AD3: 28.42 | AE3: 0 | AF3: 28.42 | AG3: 0.195
A4: 302621 | B4: FILIAL SP | C4: 46289 | D4: 46293 | F4: 37902-1 | G4: ANSELL BRAZIL L | H4: MARLON MARQUES | I4: 2258.5 | J4: EXPRESSO_250 | K4: CTE NORMAL | L4: CRICIUMA - SC | M4: 145.78 | N4: 2 | O4: 10.82 | P4: FILIAL SP | Q4: 11.22 | R4: MF EXPRESS TRANSPORTE ROD | S4: 51.02 | T4: G.S CITRUS COMERCIO ATACA | U4: 5.11 | V4: 17.49 | W4: 0 | X4: 0 | Y4: 1.13 | Z4: 0 | AA4: 85.97 | AB4: 59.81 | AC4: 37.9 | AD4: 21.91 | AE4: 0 | AF4: 21.91 | AG4: 0.1503
A5: 302857 | B5: FILIAL SP | C5: 46293 | D5: 46293 | F5: 37966-1 | G5: ANSELL BRAZIL L | H5: MARLON MARQUES | I5: 3726.37 | J5: EXPRESSO_250 | K5: CTE NORMAL | L5: GARUVA - SC | M5: 115.39 | N5: 2 | O5: 13.25 | P5: FILIAL SP | Q5: 5.35 | R5: HELTON JOHN DA SILVA | S5: 0.09 | T5: G.S CITRUS COMERCIO ATACA | U5: 6.26 | V5: 13.85 | W5: 0 | X5: 0 | Y5: 1.86 | Z5: 0 | AA5: 27.41 | AB5: 87.98 | AC5: 30 | AD5: 57.98 | AE5: 0 | AF5: 57.98 | AG5: 0.5025
A6: 302858 | B6: FILIAL SP | C6: 46293 | D6: 46293 | F6: 37965-1 | G6: HERCULES EQUIPA | H6: MARLON MARQUES | I6: 7602.95 | J6: EXPRESSO_250 | K6: CTE NORMAL | L6: GARUVA - SC | M6: 166.74 | N6: 31 | O6: 49.6 | P6: FILIAL SP | Q6: 20.02 | R6: HELTON JOHN DA SILVA | S6: 0.33 | T6: G.S CITRUS COMERCIO ATACA | U6: 23.44 | V6: 20.01 | W6: 0 | X6: 0 | Y6: 3.8 | Z6: 0 | AA6: 67.6 | AB6: 99.14 | AC6: 43.35 | AD6: 55.79 | AE6: 0 | AF6: 55.79 | AG6: 0.3346
A7: 302859 | B7: FILIAL SP | C7: 46293 | D7: 46293 | F7: 37964-1 | G7: ANSELL BRAZIL L | H7: MARLON MARQUES | I7: 16768.66 | J7: EXPRESSO_250 | K7: CTE NORMAL | L7: GARUVA - SC | M7: 367.76 | N7: 9 | O7: 59.62 | P7: FILIAL SP | Q7: 24.06 | R7: HELTON JOHN DA SILVA | S7: 0.39 | T7: G.S CITRUS COMERCIO ATACA | U7: 28.18 | V7: 44.13 | W7: 0 | X7: 0 | Y7: 8.38 | Z7: 0 | AA7: 105.14 | AB7: 262.62 | AC7: 95.62 | AD7: 167 | AE7: 0 | AF7: 167 | AG7: 0.4541
A8: 302860 | B8: FILIAL SP | C8: 46293 | D8: 46293 | F8: 37963-1 | G8: ANSELL BRAZIL L | H8: MARLON MARQUES | I8: 3726.37 | J8: EXPRESSO_250 | K8: CTE NORMAL | L8: GARUVA - SC | M8: 115.39 | N8: 2 | O8: 13.25 | P8: FILIAL SP | Q8: 5.35 | R8: HELTON JOHN DA SILVA | S8: 0.09 | T8: G.S CITRUS COMERCIO ATACA | U8: 6.26 | V8: 13.85 | W8: 0 | X8: 0 | Y8: 1.86 | Z8: 0 | AA8: 27.41 | AB8: 87.98 | AC8: 30 | AD8: 57.98 | AE8: 0 | AF8: 57.98 | AG8: 0.5025
A9: 302861 | B9: FILIAL SP | C9: 46293 | D9: 46293 | F9: 37962-1 | G9: ANSELL BRAZIL L | H9: MARLON MARQUES | I9: 11471.58 | J9: EXPRESSO_250 | K9: CTE NORMAL | L9: SAO JOSE - SC | M9: 237.25 | N9: 5 | O9: 48.82 | P9: FILIAL SP | Q9: 19.7 | R9: MF EXPRESS TRANSPORTE ROD | S9: 83.04 | T9: G.S CITRUS COMERCIO ATACA | U9: 23.08 | V9: 28.47 | W9: 0 | X9: 0 | Y9: 5.74 | Z9: 0 | AA9: 160.03 | AB9: 77.22 | AC9: 61.68 | AD9: 15.54 | AE9: 0 | AF9: 15.54 | AG9: 0.0655
A10: 302863 | B10: FILIAL SP | C10: 46293 | D10: 46293 | F10: 37960-1 | G10: ANSELL BRAZIL L | H10: MARLON MARQUES | I10: 72120.4 | J10: EXPRESSO_250 | K10: CTE NORMAL | L10: INDAIAL - SC | M10: 1581.73 | N10: 37 | O10: 358.28 | P10: FILIAL SP | Q10: 144.6 | R10: JOSENIR DE SOUZA CUNHA | S10: 0 | T10: G.S CITRUS COMERCIO ATACA | U10: 228.61 | V10: 189.81 | W10: 0 | X10: 0 | Y10: 36.06 | Z10: 0 | AA10: 599.08 | AB10: 982.65 | AC10: 411.25 | AD10: 571.4 | AE10: 0 | AF10: 571.4 | AG10: 0.3613
A11: 302864 | B11: FILIAL SP | C11: 46293 | D11: 46293 | F11: 37959-1 | G11: ANSELL BRAZIL L | H11: MARLON MARQUES | I11: 9315.92 | J11: EXPRESSO_250 | K11: CTE NORMAL | L11: GARUVA - SC | M11: 204.32 | N11: 5 | O11: 33.12 | P11: FILIAL SP | Q11: 13.37 | R11: HELTON JOHN DA SILVA | S11: 0.22 | T11: G.S CITRUS COMERCIO ATACA | U11: 15.65 | V11: 24.52 | W11: 0 | X11: 0 | Y11: 4.66 | Z11: 0 | AA11: 58.42 | AB11: 145.9 | AC11: 53.12 | AD11: 92.78 | AE11: 0 | AF11: 92.78 | AG11: 0.4541
A12: 302865 | B12: FILIAL SP | C12: 46293 | D12: 46293 | F12: 37958-1 | G12: ANSELL BRAZIL L | H12: MARLON MARQUES | I12: 2861.89 | J12: EXPRESSO_250 | K12: CTE NORMAL | L12: SAO BENTO DO SUL - SC | M12: 145.78 | N12: 4 | O12: 32 | P12: FILIAL SP | Q12: 12.92 | R12: HELTON JOHN DA SILVA | S12: 0.21 | T12: G.S CITRUS COMERCIO ATACA | U12: 15.13 | V12: 17.49 | W12: 0 | X12: 0 | Y12: 1.43 | Z12: 0 | AA12: 47.18 | AB12: 98.6 | AC12: 37.9 | AD12: 60.7 | AE12: 0 | AF12: 60.7 | AG12: 0.4164
A13: 302866 | B13: FILIAL SP | C13: 46293 | D13: 46293 | F13: 37957-1 | G13: HERCULES EQUIPA | H13: MARLON MARQUES | I13: 4432.33 | J13: EXPRESSO_250 | K13: CTE NORMAL | L13: GARUVA - SC | M13: 115.39 | N13: 3 | O13: 20.4 | P13: FILIAL SP | Q13: 8.23 | R13: HELTON JOHN DA SILVA | S13: 0.13 | T13: G.S CITRUS COMERCIO ATACA | U13: 9.64 | V13: 13.85 | W13: 0 | X13: 0 | Y13: 2.22 | Z13: 0 | AA13: 34.07 | AB13: 81.32 | AC13: 30 | AD13: 51.32 | AE13: 0 | AF13: 51.32 | AG13: 0.4448
... A31: 4284 | B31: MATRIZ | C31: 46294 | D31: 46294 | F31: 4060-1 | G31: IND.E COM.LEAL | H31: URIEL CORREA | I31: 10752 | J31: LEAL SP X SC | K31: CTE NORMAL | L31: NAVEGANTES - SC | M31: 134.42 | N31: 14 | O31: 449 | P31: MATRIZ | Q31: 0 | R31: N/D | S31: 0 | T31: G.S CITRUS COMERCIO ATACA | U31: 51.72 | V31: 0 | W31: 0 | X31: 0 | Y31: 0 | Z31: 0 | AA31: 51.72 | AB31: 82.7 | AC31: 34.95 | AD31: 47.75 | AE31: 1.34 | AF31: 46.41 | AG31: 0.3453

Sheet Análise
E1: FATURAMENTO
E2: Faturamento | H2: Peso | J2: Venda KG | M2: Veículo | P2: Peso Veículo | S2: Taxa Ocupação Veículo
E3: ='Resumo Detalhado'!B2 -> 13590.7 | H3: ='Resumo Detalhado'!C2 -> 4256.41 | J3: =E3/H3 -> 3.192996 | M3: Carreta | P3: 22000 | S3: =MIN(H3/P3,1) -> 0.19347318
E5: CUSTO VARIÁVEL SINTÉTICO
E6: C.Variável Total | J6: Custo KG Total CV | M6: % Fat x C.V Total | P6: Custo Total | S6: Custo KG Total
E7: =E11+K11+Q11 -> 3330.33 | J7: =E7/H3 -> 0.78242697 | M7: =E7/E3 -> 0.24504477 | P7: =E11+K11+Q11+E15+K15+Q15+E19+H19+K19 -> 8601.78 | S7: =P7/J3 -> 2693.9527
E9: CUSTO VARIÁVEL ANÁLITICO
E10: C.Transf. | H10: Custo KG Transf. | K10: C.Entrega | N10: Custo KG Entrega | Q10: C.Coleta | T10: Custo KG Coleta
E11: 1850 | H11: =E11/H3 -> 0.43463858 | K11: ='Resumo Detalhado'!E2 -> 304.47 | N11: =K11/H3 -> 0.071532113 | Q11: ='Resumo Detalhado'!D2 -> 1175.86 | T11: =Q11/H3 -> 0.27625628 | W11: TIPO DE VEÍCULO | Y11: CAP.PESO
W12: Carreta | Y12: 22000
E13: IMPOSTOS | W13: Truck | Y13: 11000
E14: C.Icms | K14: I.Federais + c.Fixo | W14: Toco | Y14: 6000
E15: ='Resumo Detalhado'!H2 -> 1459.38 | K15: ='Resumo Detalhado'!K2 -> 3533.54 | W15: 3/4 | Y15: 3500
W16: Van | Y16: 1200
E17: OUTROS CUSTOS | O17: TARGET
E18: C.Seguro | H18: C.M.O(Outros) | K18: C.Comissão | N18: TRECHO | S18: VALOR | W18: STATUS DA CONTRATAÇÃO
E19: ='Resumo Detalhado'!I2 -> 264.24 | H19: ='Resumo Detalhado'!J2 -> 0 | K19: ='Resumo Detalhado'!L2 -> 14.29 | N19: Sao Paulo-Sp X Itajai-Sccarreta | S19: 1850 | W19: =IF(E11=S19,"NO TARGET",IF(E11<S19,"ABAIXO DO TARGET",IF(E11>S19,"FORA DO TARGET"))) -> NO TARGET
E21: RESULTADO
E22: Resultado Operacional | N22: Margem Bruta
E23: ='Resumo Detalhado'!M2 -> 4929.66 | N23: =E23/E3 -> 0.36272304

Sheet Resumo Detalhado
A1: SERVICO | B1: (Tudo)
B2: =SUM(B6:B5000) -> 13590.7 | C2: =SUM(C6:C5000) -> 4256.41 | D2: =SUM(D6:D5000) -> 1175.86 | E2: =SUM(E6:E5000) -> 304.47 | F2: =SUM(F6:F5000) -> 1909.26 | H2: =SUM(H6:H5000) -> 1459.38 | I2: =SUM(I6:I5000) -> 264.24 | J2: =SUM(J6:J5000) -> 0 | K2: =SUM(K6:K5000) -> 3533.54 | L2: =SUM(L6:L5000) -> 14.29 | M2: =SUM(M6:M5000) -> 4929.66
B3: Valores
A4: CLIENTE | B4: FATURAMENTO | C4: PESO FAT. | D4: C.COLETA | E4: C.ENTREGA | F4: C.TRANSF | G4: META C.VARIÁVEL | H4: C.ICMS | I4: C.SEGURO | J4: C.OUTROS | K4: IMPOSTO. | L4: C.COMIS | M4: Resultado Oper. | N4: MARGEM BRUTA.
A5: ANSELL BRAZIL L
A6: 302534 | B6: 299.17 | C6: 86.36 | D6: 89.58 | E6: 104.71 | F6: 40.82 | G6: 0.78587425 | H6: 35.9 | I6: 6.48 | J6: 0 | K6: 77.78 | L6: 0 | M6: -56.1 | N6: -0.1875188
A7: 302617 | B7: 145.78 | C7: 6.62 | D7: 6.87 | E7: 51.02 | F7: 3.13 | G7: 0.41857594 | H7: 17.49 | I7: 0.95 | J7: 0 | K7: 37.9 | L7: 0 | M7: 28.42 | N7: 0.1949513
A8: 302621 | B8: 145.78 | C8: 10.82 | D8: 11.22 | E8: 51.02 | F8: 5.11 | G8: 0.46199753 | H8: 17.49 | I8: 1.13 | J8: 0 | K8: 37.9 | L8: 0 | M8: 21.91 | N8: 0.15029497
A9: 302857 | B9: 115.39 | C9: 13.25 | D9: 5.35 | E9: 0.09 | F9: 6.26 | G9: 0.10139527 | H9: 13.85 | I9: 1.86 | J9: 0 | K9: 30 | L9: 0 | M9: 57.98 | N9: 0.50246988
A10: 302859 | B10: 367.76 | C10: 59.62 | D10: 24.06 | E10: 0.39 | F10: 28.18 | G10: 0.14310964 | H10: 44.13 | I10: 8.38 | J10: 0 | K10: 95.62 | L10: 0 | M10: 167 | N10: 0.4541005
A11: 302860 | B11: 115.39 | C11: 13.25 | D11: 5.35 | E11: 0.09 | F11: 6.26 | G11: 0.10139527 | H11: 13.85 | I11: 1.86 | J11: 0 | K11: 30 | L11: 0 | M11: 57.98 | N11: 0.50246988
A12: 302861 | B12: 237.25 | C12: 48.82 | D12: 19.7 | E12: 83.04 | F12: 23.08 | G12: 0.53032666 | H12: 28.47 | I12: 5.74 | J12: 0 | K12: 61.68 | L12: 0 | M12: 15.54 | N12: 0.065500527
A13: 302863 | B13: 1581.73 | C13: 358.28 | D13: 144.6 | E13: 0 | F13: 228.61 | G13: 0.23595051 | H13: 189.81 | I13: 36.06 | J13: 0 | K13: 411.25 | L13: 0 | M13: 571.4 | N13: 0.36125002
A14: 302864 | B14: 204.32 | C14: 33.12 | D14: 13.37 | E14: 0.22 | F14: 15.65 | G14: 0.14310885 | H14: 24.52 | I14: 4.66 | J14: 0 | K14: 53.12 | L14: 0 | M14: 92.78 | N14: 0.45409162
A15: 302865 | B15: 145.78 | C15: 32 | D15: 12.92 | E15: 0.21 | F15: 15.13 | G15: 0.19385375 | H15: 17.49 | I15: 1.43 | J15: 0 | K15: 37.9 | L15: 0 | M15: 60.7 | N15: 0.41638085
A16: 302867 | B16: 163.44 | C16: 26.5 | D16: 10.7 | E16: 0.17 | F16: 12.53 | G16: 0.14317181 | H16: 19.61 | I16: 3.73 | J16: 0 | K16: 42.49 | L16: 0 | M16: 74.21 | N16: 0.45405042
A17: 302868 | B17: 355.98 | C17: 52.99 | D17: 21.39 | E17: 0.35 | F17: 25.05 | G17: 0.13143997 | H17: 42.72 | I17: 8.12 | J17: 0 | K17: 92.55 | L17: 0 | M17: 165.8 | N17: 0.4657565
... A26: 302894 | B26: 1188.66 | C26: 114.05 | D26: 46.03 | E26: 0.75 | F26: 53.91 | G26: 0.084708832 | H26: 142.64 | I26: 27.1 | J26: 0 | K26: 309.05 | L26: 0 | M26: 609.18 | N26: 0.51249306
A27: HERCULES EQUIPA
A28: 302858 | B28: 166.74 | C28: 49.6 | D28: 20.02 | E28: 0.33 | F28: 23.44 | G28: 0.26262445 | H28: 20.01 | I28: 3.8 | J28: 0 | K28: 43.35 | L28: 0 | M28: 55.79 | N28: 0.33459278
A29: 302866 | B29: 115.39 | C29: 20.4 | D29: 8.23 | E29: 0.13 | F29: 9.64 | G29: 0.15599272 | H29: 13.85 | I29: 2.22 | J29: 0 | K29: 30 | L29: 0 | M29: 51.32 | N29: 0.44475258
A30: 302870 | B30: 115.39 | C30: 2.1 | D30: 0.85 | E30: 0.01 | F30: 0.99 | G30: 0.016032585 | H30: 13.85 | I30: 0.99 | J30: 0 | K30: 30 | L30: 0 | M30: 68.7 | N30: 0.59537222
A31: 302872 | B31: 115.39 | C31: 2.1 | D31: 0.85 | E31: 0.01 | F31: 0.99 | G31: 0.016032585 | H31: 13.85 | I31: 0.99 | J31: 0 | K31: 30 | L31: 0 | M31: 68.7 | N31: 0.59537222
A32: IND.E COM.LEAL
A33: 4280 | B33: 87.07 | C33: 273 | D33: 0 | E33: 0 | F33: 33.5 | G33: 0.3847479 | H33: 0 | I33: 0 | J33: 0 | K33: 22.64 | L33: 0.87 | M33: 30.06 | N33: 0.34523946
A34: 4281 | B34: 112.52 | C34: 100 | D34: 0 | E34: 0 | F34: 43.3 | G34: 0.38482048 | H34: 0 | I34: 0 | J34: 0 | K34: 29.26 | L34: 1.13 | M34: 38.83 | N34: 0.34509421
A35: 4282 | B35: 915.12 | C35: 600 | D35: 0 | E35: 0 | F35: 352.13 | G35: 0.38479107 | H35: 0 | I35: 0 | J35: 0 | K35: 237.93 | L35: 9.15 | M35: 315.91 | N35: 0.34521156
A36: 4283 | B36: 180.21 | C36: 84 | D36: 0 | E36: 0 | F36: 69.34 | G36: 0.38477332 | H36: 0 | I36: 0 | J36: 0 | K36: 46.85 | L36: 1.8 | M36: 62.22 | N36: 0.34526386
A37: 4284 | B37: 134.42 | C37: 449 | D37: 0 | E37: 0 | F37: 51.72 | G37: 0.38476417 | H37: 0 | I37: 0 | J37: 0 | K37: 34.95 | L37: 1.34 | M37: 46.41 | N37: 0.34526112
A38: (vazio)
A39: (vazio) | G39: #DIV/0! | M39: 0 | N39: #DIV/0!

Sheet Resumo Detalhado Grafico
A1: SERVICO | B1: (Tudo)
B2: =SUM(B6:B5000) -> 1942.25 | C2: =SUM(C6:C5000) -> 737.94
B3: Valores
A4: CLIENTE | B4: Faturamento. | C4: Resultado Oper.
A5: ANSELL BRAZIL L | B5: 11648.45 | C5: 4191.72
A6: HERCULES EQUIPA | B6: 512.91 | C6: 244.51
A7: IND.E COM.LEAL | B7: 1429.34 | C7: 493.43
A8: (vazio) | C8: 0

Sheet Target
A1: TRECHO | B1: TIPO VEÍCULO | C1: CONCATENADO | D1: VALOR
A2: Ascurra-Sc X Itajai-Sc | B2: 3/4 | C2: Ascurra-Sc X Itajai-Sc3/4 | D2: 800
A3: Barueri-Sp X São Paulo-Sp | B3: truck | C3: Barueri-Sp X São Paulo-Sptruck | D3: 900
A4: Belo Horizonte-Mg X Garuva-Sc | B4: van | C4: Belo Horizonte-Mg X Garuva-Scvan | D4: 4300
A5: Belo Horizonte-Mg X Itajai-Sc | B5: fiorino | C5: Belo Horizonte-Mg X Itajai-Scfiorino | D5: 3500
A6: Biguaçu-Sc X São Paulo-Sp | B6: van | C6: Biguaçu-Sc X São Paulo-Spvan | D6: 2500
A7: Blumenau-Sc X Guarulhos-Sp | B7: carreta | C7: Blumenau-Sc X Guarulhos-Spcarreta | D7: 5500
A8: Blumenau-Sc X Guarulhos-Sp | B8: truck | C8: Blumenau-Sc X Guarulhos-Sptruck | D8: 4100
A9: Blumenau-Sc X Suzano-Sp | B9: truck | C9: Blumenau-Sc X Suzano-Sptruck | D9: 4300
A10: Camboriu-Sc X Cabo de Santo Agostinho-Pe | B10: 3/4 | C10: Camboriu-Sc X Cabo de Santo Agostinho-Pe3/4 | D10: 14800
A11: Camboriu-Sc X Cabo de Santo Agostinho-Pe | B11: truck | C11: Camboriu-Sc X Cabo de Santo Agostinho-Petruck | D11: 18000
A12: Camboriu-Sc X Cabo de Santo Agostinho-Pe | B12: carreta | C12: Camboriu-Sc X Cabo de Santo Agostinho-Pecarreta | D12: 25000
A13: Camboriu-Sc X Cajamar-Sp | B13: 3/4 | C13: Camboriu-Sc X Cajamar-Sp3/4 | D13: 3200
... A176: São Paulo-Sp X São Paulo-Sp | B176: carreta | C176: São Paulo-Sp X São Paulo-Spcarreta | D176: 1500
A177: Navegantes-Sc X Cajamar-Sp | B177: 46085 | C177: Navegantes-Sc X Cajamar-Sp3/4 | D177: 3200
A178: Navegantes-Sc X Guarulhos-Sp | B178: truck | C178: Navegantes-Sc X Guarulhos-Sptruck | D178: 4100
A179: Itajai-Sc X Guarulhos-Sp | B179: toco | C179: Itajai-Sc X Guarulhos-Sptoco | D179: 3800
A180: Sao Paulo-Sp X Goiania-Go | B180: truck | C180: Sao Paulo-Sp X Goiania-Gotruck | D180: 5500
A181: Itajai-Sc X Sao Paulo-Sp | B181: truck | C181: Itajai-Sc X Sao Paulo-Sptruck | D181: 4100
A182: Sao Paulo-Sp X Goiania-Go | B182: 46085 | C182: São Paulo-Sp X Goiania-Go3/4 | D182: 3500
A183: São Paulo-Sp X Cascavel-Pr | B183: truck | C183: São Paulo-Sp X Cascavel-Prtruck | D183: 5000
C184: São Paulo-Sp X Itajai-Sctruck | D184: 2500
C185: Araraquara-Sp X Santos-Sp3/4 | D185: 1800
C186: Campinas-Sp X Suzano-Spcarreta | D186: 2500
C187: Garuva-Sc X Itajai-Sc3/4 | D187: 800
C188: Guarulhos-Sp X São Paulo-Sptruck | D188: 1200
C189: Itajai-Sc X Arapongas-Pr3/4 | D189: 3200
C190: Itajai-Sc X Balneario Camboriu-Scvan | D190: 580
C191: Itajai-Sc X Blumenau-Scfiorino | D191: 400
C192: Itajai-Sc X Blumenau-Sctoco | D192: 900
C193: Itajai-Sc X Blumenau-Sctruck | D193: 1200
C194: Itajai-Sc X Blumenau-Sccarreta | D194: 1500
C195: Itajai-Sc X Curitiba-Prtruck | D195: 2200
... C364: Itajai-Sc X Serra-EsCarreta | D364: 13000
